truedata/__init__.py
truedata/analytics/TD_analytics.py
truedata/analytics/__init__.py
truedata/analytics/decorators.py
truedata/history/Historical_REST.py
truedata/history/TD_hist.py
truedata/history/__init__.py
truedata/history/utils.py
truedata/tests/__init__.py
truedata/tests/defaults.py
truedata/websocket/TD_chain.py
truedata/websocket/TD_live.py
truedata/websocket/TD_ws.py
truedata/websocket/__init__.py
truedata/websocket/compression_map.py
truedata/websocket/constants.py
truedata/websocket/exceptions.py
truedata/websocket/utils.py
truedata-7.0.0.dist-info/LICENSE
truedata-7.0.0.dist-info/METADATA
truedata-7.0.0.dist-info/WHEEL
truedata-7.0.0.dist-info/top_level.txt
truedata-7.0.0.dist-info/RECORD
