Metadata-Version: 2.2
Name: truedata
Version: 7.0.0
Summary: Truedata's Official Python Package
Home-page: https://github.com/kapilmar/truedata-ws
Author: Nahas N
Author-email: nahas@truedata.in
Classifier: Programming Language :: Python :: 3.10
Classifier: License :: OSI Approved :: GNU General Public License v3 (GPLv3)
Classifier: Operating System :: OS Independent
Requires-Python: >=3.10
License-File: LICENSE
Requires-Dist: websocket-client>=0.58.0
Requires-Dist: colorama>=0.4.3
Requires-Dist: python-dateutil>=2.8.1
Requires-Dist: pandas>=1.0.3
Requires-Dist: requests>=2.25.0
Requires-Dist: lz4>=3.1.3
Requires-Dist: tqdm>=4.66.6
Dynamic: author
Dynamic: author-email
Dynamic: classifier
Dynamic: description
Dynamic: description-content-type
Dynamic: home-page
Dynamic: requires-dist
Dynamic: requires-python
Dynamic: summary
